darc/__init__.py
darc/__main__.py
darc/_compat.py
darc/_datetime.py
darc/_robotparser.py
darc/_typing.py
darc/const.py
darc/crawl.py
darc/db.py
darc/error.py
darc/link.py
darc/logging.py
darc/parse.py
darc/process.py
darc/py.typed
darc/requests.py
darc/save.py
darc/selenium.py
darc/signal.py
darc/submit.py
darc/model/__init__.py
darc/model/abc.py
darc/model/utils.py
darc/model/tasks/__init__.py
darc/model/tasks/hostname.py
darc/model/tasks/requests.py
darc/model/tasks/selenium.py
darc/model/web/__init__.py
darc/model/web/hostname.py
darc/model/web/hosts.py
darc/model/web/requests.py
darc/model/web/robots.py
darc/model/web/selenium.py
darc/model/web/sitemap.py
darc/model/web/url.py
darc/proxy/__init__.py
darc/proxy/bitcoin.py
darc/proxy/data.py
darc/proxy/ed2k.py
darc/proxy/ethereum.py
darc/proxy/freenet.py
darc/proxy/i2p.py
darc/proxy/irc.py
darc/proxy/magnet.py
darc/proxy/mail.py
darc/proxy/null.py
darc/proxy/script.py
darc/proxy/tel.py
darc/proxy/tor.py
darc/proxy/ws.py
darc/proxy/zeronet.py
darc/sites/__init__.py
darc/sites/_abc.py
darc/sites/bitcoin.py
darc/sites/data.py
darc/sites/default.py
darc/sites/ed2k.py
darc/sites/ethereum.py
darc/sites/irc.py
darc/sites/magnet.py
darc/sites/mail.py
darc/sites/script.py
darc/sites/tel.py
darc/sites/ws.py
python_darc-1.0.3.dist-info/LICENSE
python_darc-1.0.3.dist-info/METADATA
python_darc-1.0.3.dist-info/WHEEL
python_darc-1.0.3.dist-info/entry_points.txt
python_darc-1.0.3.dist-info/top_level.txt
python_darc-1.0.3.dist-info/RECORD
