Metadata-Version: 2.1
Name: python-darc
Version: 1.0.3
Summary: Darkweb crawler & search engine.
Home-page: https://github.com/JarryShaw/darc
Download-URL: https://github.com/JarryShaw/darc/archive/v1.0.3.tar.gz
Author: Jarry Shaw
Author-email: jarryshaw@icloud.com
Maintainer: Jarry Shaw
Maintainer-email: jarryshaw@icloud.com
License: BSD 3-Clause License
Keywords: darkweb,crawler
Platform: any
Classifier: Development Status :: 5 - Production/Stable
Classifier: Intended Audience :: Developers
Classifier: License :: OSI Approved :: BSD License
Classifier: Natural Language :: English
Classifier: Operating System :: OS Independent
Classifier: Programming Language :: Python
Classifier: Programming Language :: Python :: 3.6
Classifier: Programming Language :: Python :: 3.7
Classifier: Programming Language :: Python :: 3.8
Classifier: Programming Language :: Python :: 3 :: Only
Classifier: Topic :: Software Development
Classifier: Topic :: Utilities
Classifier: Typing :: Typed
Requires-Python: >=3.6
License-File: LICENSE
Requires-Dist: beautifulsoup4[html5lib]
Requires-Dist: file-magic
Requires-Dist: peewee
Requires-Dist: pottery
Requires-Dist: psutil
Requires-Dist: python-datauri
Requires-Dist: redis[hiredis]
Requires-Dist: requests-futures
Requires-Dist: requests[socks]
Requires-Dist: selenium <4
Requires-Dist: stem
Requires-Dist: typing-extensions
Requires-Dist: dataclasses ; python_version < "3.7"
Provides-Extra: mysql
Requires-Dist: PyMySQL[rsa] ; extra == 'mysql'
Provides-Extra: postgresql
Requires-Dist: psycopg2 ; extra == 'postgresql'
Provides-Extra: sqlite
Requires-Dist: pysqlite3 ; extra == 'sqlite'
